redfish_hp_ilo/__init__.py
redfish_hp_ilo/api.py
redfish_hp_ilo/g9.py
redfish_hp_ilo/standard.py
redfish_hp_ilo/wrappers.py
redfish_hp_ilo-0.1.0.dist-info/LICENSE
redfish_hp_ilo-0.1.0.dist-info/METADATA
redfish_hp_ilo-0.1.0.dist-info/WHEEL
redfish_hp_ilo-0.1.0.dist-info/top_level.txt
redfish_hp_ilo-0.1.0.dist-info/RECORD
